orbitlab/__init__.py
orbitlab/orbit_main.py
orbitlab/orbit_utils/__init__.py
orbitlab/orbit_utils/face_ids.py
orbitlab/orbit_websocket/__init__.py
orbitlab/orbit_websocket/websocket_client.py
orbitlab_python-0.0.6.dist-info/METADATA
orbitlab_python-0.0.6.dist-info/WHEEL
orbitlab_python-0.0.6.dist-info/top_level.txt
orbitlab_python-0.0.6.dist-info/zip-safe
orbitlab_python-0.0.6.dist-info/RECORD
