Metadata-Version: 2.4
Name: orbitlab-python
Version: 0.0.6
Summary: TODO: package description
Maintainer: Kalebu
Maintainer-email: calebndatimana@gmail.com
License: TODO: License declaration
Requires-Dist: setuptools
Requires-Dist: numpy
Requires-Dist: opencv-python
Dynamic: license
Dynamic: maintainer
Dynamic: maintainer-email
Dynamic: requires-dist
Dynamic: summary
